jonnys_single_file_package/__init__.py
jonnys_single_file_package-0.0.1.dist-info/METADATA
jonnys_single_file_package-0.0.1.dist-info/WHEEL
jonnys_single_file_package-0.0.1.dist-info/entry_points.txt
jonnys_single_file_package-0.0.1.dist-info/RECORD
