Metadata-Version: 2.1
Name: jonnys-single-file-package
Version: 0.0.1
Summary: A single file package I gone and made
Author: jonny
License-Expression: GPL-3.0
Requires-Python: >=3.8
Requires-Dist: numpy>=1.24.0
